{
    "key": "group_5cd08e723f796",
    "title": "Feauture page",
    "fields": [
        {
            "key": "field_5cd08e7c77808",
            "label": "Designer",
            "name": "designer",
            "type": "post_object",
            "instructions": "",
            "required": 0,
            "conditional_logic": 0,
            "wrapper": {
                "width": "",
                "class": "",
                "id": ""
            },
            "post_type": [
                "designers"
            ],
            "taxonomy": "",
            "allow_null": 0,
            "multiple": 0,
            "return_format": "id",
            "ui": 1
        },
        {
            "key": "field_5cd08ef8ee766",
            "label": "FB Image",
            "name": "fb_image",
            "type": "text",
            "instructions": "",
            "required": 0,
            "conditional_logic": 0,
            "wrapper": {
                "width": "",
                "class": "",
                "id": ""
            },
            "default_value": "",
            "maxlength": "",
            "placeholder": "",
            "prepend": "",
            "append": ""
        },
        {
            "key": "field_5cd090a9ee767",
            "label": "FB Title",
            "name": "fb_title",
            "type": "text",
            "instructions": "",
            "required": 0,
            "conditional_logic": 0,
            "wrapper": {
                "width": "",
                "class": "",
                "id": ""
            },
            "default_value": "",
            "placeholder": "",
            "prepend": "",
            "append": "",
            "maxlength": ""
        },
        {
            "key": "field_5cd090b6ee768",
            "label": "FB Description",
            "name": "fb_description",
            "type": "text",
            "instructions": "",
            "required": 0,
            "conditional_logic": 0,
            "wrapper": {
                "width": "",
                "class": "",
                "id": ""
            },
            "default_value": "",
            "placeholder": "",
            "prepend": "",
            "append": "",
            "maxlength": ""
        }
    ],
    "location": [
        [
            {
                "param": "post_template",
                "operator": "==",
                "value": "page-designers.php"
            }
        ]
    ],
    "menu_order": 0,
    "position": "normal",
    "style": "default",
    "label_placement": "top",
    "instruction_placement": "label",
    "hide_on_screen": "",
    "active": 1,
    "description": "",
    "modified": 1557176778
}